{
  "wareHouseWidth": 30,
  "wareHouseHeight": 30,
  "WAREHOUSE_BOUNDS": {
    "startX": 0,
    "startY": 0,
    "endX": 29,
    "endY": 29
  },
  "binSizeInMeters": 1,
  "productsPerBin": 15,
  "SKUsPerBin": 9,
  "SKUs": 20,
  "productsInStock": 2000,
  "skuDistribution": [
    [
      20.5,
      50.0
    ],
    [
      9.5,
      30.0
    ],
    [
      70.0,
      20.0
    ]
  ],
  "isRandomProductDistribution": true,
  "numberOfRobots": 15,
  "robotTopSpeed": 3.0,
  "robotAcceleration": 0.8,
  "robotDeceleration": 2.0,
  "robotMinimumSpeed": 0.1,
  "robotPickUpSpeedInSeconds": 3,
  "robotDeliverToPickInSeconds": 12,
  "collisionDetectedEnabled": true,
  "robotPlacementPattern": {
    "patternType": "STACKED_LINES",
    "padding": 1,
    "bounds": {
      "startX": 0,
      "startY": 0,
      "endX": 29,
      "endY": 29
    }
  },
  "pickerPlacementPattern": {
    "patternType": "SPIRAL",
    "padding": 8,
    "bounds": {
      "startX": 0,
      "startY": 0,
      "endX": 29,
      "endY": 29
    },
    "customPoints": [
      [
        1,
        0
      ],
      [
        2,
        0
      ],
      [
        4,
        0
      ],
      [
        6,
        0
      ],
      [
        8,
        0
      ],
      [
        10,
        0
      ],
      [
        12,
        0
      ],
      [
        14,
        0
      ],
      [
        16,
        0
      ],
      [
        18,
        0
      ],
      [
        20,
        0
      ],
      [
        22,
        0
      ],
      [
        24,
        0
      ],
      [
        26,
        0
      ],
      [
        28,
        0
      ]
    ]
  },
  "numberOfPickers": 10,
  "pickerPoints": [
    [
      0,
      0
    ],
    [
      2,
      0
    ],
    [
      4,
      0
    ],
    [
      6,
      0
    ],
    [
      8,
      0
    ],
    [
      10,
      0
    ],
    [
      12,
      0
    ],
    [
      14,
      0
    ],
    [
      16,
      0
    ],
    [
      18,
      0
    ],
    [
      20,
      0
    ],
    [
      22,
      0
    ],
    [
      24,
      0
    ],
    [
      26,
      0
    ],
    [
      28,
      0
    ]
  ],
  "secondsBetweenOrders": 9,
  "orderGoal": 50,
  "productsPerOrder": 4
}